{
  "matrix_a": {
    "A1": {
      "total": 20,
      "counts": {
        "semantic_role_composition": 8,
        "imagery_transformation": 4,
        "direct_expression": 8
      },
      "ratios": {
        "semantic_role_composition": 0.4,
        "imagery_transformation": 0.2,
        "direct_expression": 0.4
      },
      "meets_threshold": true
    },
    "A2": {
      "total": 20,
      "counts": {
        "imagery_transformation": 4,
        "semantic_role_composition": 8,
        "direct_expression": 8
      },
      "ratios": {
        "imagery_transformation": 0.2,
        "semantic_role_composition": 0.4,
        "direct_expression": 0.4
      },
      "meets_threshold": true
    },
    "A3": {
      "total": 20,
      "counts": {
        "direct_expression": 8,
        "semantic_role_composition": 8,
        "imagery_transformation": 4
      },
      "ratios": {
        "direct_expression": 0.4,
        "semantic_role_composition": 0.4,
        "imagery_transformation": 0.2
      },
      "meets_threshold": true
    },
    "A4": {
      "total": 20,
      "counts": {
        "semantic_role_composition": 8,
        "direct_expression": 7,
        "imagery_transformation": 5
      },
      "ratios": {
        "semantic_role_composition": 0.4,
        "direct_expression": 0.35,
        "imagery_transformation": 0.25
      },
      "meets_threshold": true
    },
    "A5": {
      "total": 20,
      "counts": {
        "imagery_transformation": 4,
        "direct_expression": 9,
        "semantic_role_composition": 7
      },
      "ratios": {
        "imagery_transformation": 0.2,
        "direct_expression": 0.45,
        "semantic_role_composition": 0.35
      },
      "meets_threshold": true
    }
  },
  "matrix_b": {
    "B1": {
      "total": 20,
      "counts": {
        "semantic_role_composition": 8,
        "imagery_transformation": 4,
        "direct_expression": 8
      },
      "ratios": {
        "semantic_role_composition": 0.4,
        "imagery_transformation": 0.2,
        "direct_expression": 0.4
      },
      "meets_threshold": true
    },
    "B2": {
      "total": 20,
      "counts": {
        "semantic_role_composition": 8,
        "imagery_transformation": 4,
        "direct_expression": 8
      },
      "ratios": {
        "semantic_role_composition": 0.4,
        "imagery_transformation": 0.2,
        "direct_expression": 0.4
      },
      "meets_threshold": true
    },
    "B3": {
      "total": 20,
      "counts": {
        "semantic_role_composition": 8,
        "imagery_transformation": 4,
        "direct_expression": 8
      },
      "ratios": {
        "semantic_role_composition": 0.4,
        "imagery_transformation": 0.2,
        "direct_expression": 0.4
      },
      "meets_threshold": true
    },
    "B4": {
      "total": 20,
      "counts": {
        "imagery_transformation": 4,
        "semantic_role_composition": 8,
        "direct_expression": 8
      },
      "ratios": {
        "imagery_transformation": 0.2,
        "semantic_role_composition": 0.4,
        "direct_expression": 0.4
      },
      "meets_threshold": true
    },
    "B5": {
      "total": 20,
      "counts": {
        "imagery_transformation": 4,
        "semantic_role_composition": 8,
        "direct_expression": 8
      },
      "ratios": {
        "imagery_transformation": 0.2,
        "semantic_role_composition": 0.4,
        "direct_expression": 0.4
      },
      "meets_threshold": true
    }
  }
}